conftest.py
exonviz/__init__.py
exonviz/__main__.py
exonviz/cli.py
exonviz/draw.py
exonviz/exon.py
exonviz/mutalyzer.py
exonviz/py.typed
exonviz/range.py
exonviz/data/mane.txt.gz
exonviz-0.2.17.dist-info/licenses/LICENSE
exonviz-0.2.17.dist-info/METADATA
exonviz-0.2.17.dist-info/WHEEL
exonviz-0.2.17.dist-info/entry_points.txt
exonviz-0.2.17.dist-info/top_level.txt
exonviz-0.2.17.dist-info/RECORD
