Metadata-Version: 2.4
Name: exonviz
Version: 0.2.17
Summary: Visualise exons and their reading frames
Home-page: https://github.com/DCRT-LUMC/exonviz
Author: Redmar van den Berg
Author-email: RedmarvandenBerg@lumc.nl
License: AGPL-3.0
Project-URL: Changelog, https://github.com/DCRT-LUMC/exonviz/blob/main/CHANGELOG.md
Project-URL: Issue Tracker, https://github.com/DCRT-LUMC/exonviz/issues
Classifier: Development Status :: 3 - Alpha
Classifier: Intended Audience :: Developers
Classifier: License :: OSI Approved :: BSD License
Classifier: Operating System :: Unix
Classifier: Programming Language :: Python
Classifier: Programming Language :: Python :: 3
Classifier: Programming Language :: Python :: 3.10
Classifier: Programming Language :: Python :: 3.11
Classifier: Programming Language :: Python :: 3.12
Classifier: Programming Language :: Python :: 3.13
Classifier: Programming Language :: Python :: 3.14
Classifier: Topic :: Utilities
Requires-Python: >=3.10
License-File: LICENSE
Requires-Dist: svg-py
Requires-Dist: mutalyzer_crossmapper
Requires-Dist: mutalyzer_hgvs_parser
Requires-Dist: setuptools
Dynamic: author
Dynamic: author-email
Dynamic: classifier
Dynamic: description
Dynamic: description-content-type
Dynamic: home-page
Dynamic: license
Dynamic: license-file
Dynamic: project-url
Dynamic: requires-dist
Dynamic: requires-python
Dynamic: summary
